<?xml version="1.0" encoding="iso-8859-1" ?>
<!DOCTYPE rem:requirementsProject SYSTEM "C:\Program Files (x86)\REM 1.2.2\xml\REM_1_2_2.dtd">
<rem:requirementsProject
xmlns:rem="http://rem.lsi.us.es">
<rem:name>Requisitos Sistema de entregas</rem:name>
<rem:c_requirementsSpecification oid = "CRS-0001">
<rem:name>Documento de Requisitos TRATEME</rem:name>
<rem:version>
<rem:major>1</rem:major>
<rem:minor>0</rem:minor>
<rem:date>
<rem:year>2018</rem:year>
<rem:month>8</rem:month>
<rem:day>21</rem:day>
</rem:date>
</rem:version>
<rem:comments>
Ninguno
</rem:comments>
	 <rem:preparedFor organizations = "ORG-0001 "/>
	 <rem:preparedBy organizations = "ORG-0001 "/>
<rem:section
 oid = "SEC-0001">
<rem:name>
Organizaciones</rem:name>
<rem:version>
<rem:major>1</rem:major>
<rem:minor>0</rem:minor>
<rem:date>
<rem:year>2018</rem:year>
<rem:month>8</rem:month>
<rem:day>21</rem:day>
</rem:date>
</rem:version>
<rem:comments>
Ninguno</rem:comments>
<rem:level>1</rem:level>
<rem:number>1 </rem:number>
<rem:organization
 oid = "ORG-0001">
<rem:name>
Especialización en desarrollo de software</rem:name>
<rem:version>
<rem:major>1</rem:major>
<rem:minor>0</rem:minor>
<rem:date>
<rem:year>2018</rem:year>
<rem:month>8</rem:month>
<rem:day>21</rem:day>
</rem:date>
</rem:version>
<rem:comments>
Ninguno</rem:comments>
<rem:address>Universidad EAFIT</rem:address>
<rem:telephone>No aplica</rem:telephone>
<rem:fax>No aplica</rem:fax>
</rem:organization>
</rem:section>
<rem:section
 oid = "SEC-0002">
<rem:name>
Participantes</rem:name>
<rem:version>
<rem:major>1</rem:major>
<rem:minor>0</rem:minor>
<rem:date>
<rem:year>2018</rem:year>
<rem:month>8</rem:month>
<rem:day>21</rem:day>
</rem:date>
</rem:version>
<rem:comments>
Ninguno</rem:comments>
<rem:level>1</rem:level>
<rem:number>2 </rem:number>
<rem:stakeholder
 oid = "STK-0001">
<rem:name>
Andrés López</rem:name>
<rem:version>
<rem:major>1</rem:major>
<rem:minor>0</rem:minor>
<rem:date>
<rem:year>2018</rem:year>
<rem:month>8</rem:month>
<rem:day>21</rem:day>
</rem:date>
</rem:version>
<rem:comments>
Ninguno</rem:comments>
<rem:stakeholderRole>Analista desarrollador</rem:stakeholderRole>
<rem:isDeveloper/>
<rem:worksFor organization = "ORG-0001"/>
</rem:stakeholder>
<rem:stakeholder
 oid = "STK-0002">
<rem:name>
Jean Paul Galeano</rem:name>
<rem:version>
<rem:major>1</rem:major>
<rem:minor>0</rem:minor>
<rem:date>
<rem:year>2018</rem:year>
<rem:month>8</rem:month>
<rem:day>21</rem:day>
</rem:date>
</rem:version>
<rem:comments>
Ninguno</rem:comments>
<rem:stakeholderRole>Analista desarrollador</rem:stakeholderRole>
<rem:isDeveloper/>
<rem:worksFor organization = "ORG-0001"/>
</rem:stakeholder>
<rem:stakeholder
 oid = "STK-0003">
<rem:name>
Jhon Medina</rem:name>
<rem:version>
<rem:major>1</rem:major>
<rem:minor>0</rem:minor>
<rem:date>
<rem:year>2018</rem:year>
<rem:month>8</rem:month>
<rem:day>21</rem:day>
</rem:date>
</rem:version>
<rem:comments>
Ninguno</rem:comments>
<rem:stakeholderRole>Analista desarrollador</rem:stakeholderRole>
<rem:isDeveloper/>
<rem:worksFor organization = "ORG-0001"/>
</rem:stakeholder>
<rem:stakeholder
 oid = "STK-0004">
<rem:name>
Richard Ruiz</rem:name>
<rem:version>
<rem:major>1</rem:major>
<rem:minor>0</rem:minor>
<rem:date>
<rem:year>2018</rem:year>
<rem:month>8</rem:month>
<rem:day>21</rem:day>
</rem:date>
</rem:version>
<rem:comments>
Ninguno</rem:comments>
<rem:stakeholderRole>Analista desarrollador</rem:stakeholderRole>
<rem:isDeveloper/>
<rem:worksFor organization = "ORG-0001"/>
</rem:stakeholder>
</rem:section>
<rem:section
 oid = "SEC-0006">
<rem:name>
Actores</rem:name>
<rem:version>
<rem:major>1</rem:major>
<rem:minor>0</rem:minor>
<rem:date>
<rem:year>2018</rem:year>
<rem:month>8</rem:month>
<rem:day>21</rem:day>
</rem:date>
</rem:version>
<rem:comments>
Ninguno</rem:comments>
<rem:level>1</rem:level>
<rem:number>3 </rem:number>
<rem:actor
 oid = "ACT-0001">
<rem:name>
<rem:ref oid="GLO-0002">Remitente</rem:ref></rem:name>
<rem:version>
<rem:major>1</rem:major>
<rem:minor>0</rem:minor>
<rem:date>
<rem:year>2018</rem:year>
<rem:month>8</rem:month>
<rem:day>21</rem:day>
</rem:date>
</rem:version>
<rem:authors stakeholders ="STK-0003 STK-0002 STK-0001 STK-0004 "/>
<rem:sources stakeholders ="STK-0002 "/>
<rem:comments>
Ninguno</rem:comments>
<rem:actorRole>a la persona que envía la <rem:ref oid="GLO-0001">mercancía</rem:ref>.</rem:actorRole>
</rem:actor>
<rem:actor
 oid = "ACT-0002">
<rem:name>
<rem:ref oid="GLO-0003">Destinatario</rem:ref></rem:name>
<rem:version>
<rem:major>1</rem:major>
<rem:minor>0</rem:minor>
<rem:date>
<rem:year>2018</rem:year>
<rem:month>8</rem:month>
<rem:day>21</rem:day>
</rem:date>
</rem:version>
<rem:authors stakeholders ="STK-0003 STK-0002 STK-0001 STK-0004 "/>
<rem:sources stakeholders ="STK-0002 "/>
<rem:comments>
Ninguno</rem:comments>
<rem:actorRole>a la persona que recibe la <rem:ref oid="GLO-0001">mercancía</rem:ref>.</rem:actorRole>
</rem:actor>
<rem:actor
 oid = "ACT-0003">
<rem:name>
<rem:ref oid="GLO-0007">Tripulación</rem:ref></rem:name>
<rem:version>
<rem:major>1</rem:major>
<rem:minor>0</rem:minor>
<rem:date>
<rem:year>2018</rem:year>
<rem:month>8</rem:month>
<rem:day>21</rem:day>
</rem:date>
</rem:version>
<rem:authors stakeholders ="STK-0003 STK-0002 STK-0001 STK-0004 "/>
<rem:sources stakeholders ="STK-0002 "/>
<rem:comments>
Ninguno</rem:comments>
<rem:actorRole>a las personas que ejecutan el proceso logístico de transporte de <rem:ref oid="GLO-0001">mercancía</rem:ref> terrestre.</rem:actorRole>
</rem:actor>
<rem:actor
 oid = "ACT-0004">
<rem:name>
Operador</rem:name>
<rem:version>
<rem:major>1</rem:major>
<rem:minor>0</rem:minor>
<rem:date>
<rem:year>2018</rem:year>
<rem:month>8</rem:month>
<rem:day>22</rem:day>
</rem:date>
</rem:version>
<rem:authors stakeholders ="STK-0003 STK-0002 STK-0001 STK-0004 "/>
<rem:sources stakeholders ="STK-0002 "/>
<rem:comments>
Ninguno</rem:comments>
<rem:actorRole>a la empresa transportadora de <rem:ref oid="GLO-0001">mercancía</rem:ref>.</rem:actorRole>
</rem:actor>
</rem:section>
<rem:section
 oid = "SEC-0005">
<rem:name>
Objetivos</rem:name>
<rem:version>
<rem:major>1</rem:major>
<rem:minor>0</rem:minor>
<rem:date>
<rem:year>2018</rem:year>
<rem:month>8</rem:month>
<rem:day>21</rem:day>
</rem:date>
</rem:version>
<rem:comments>
Ninguno</rem:comments>
<rem:level>1</rem:level>
<rem:number>4 </rem:number>
<rem:objective
 oid = "OBJ-0001">
<rem:name>
Objetivo general</rem:name>
<rem:version>
<rem:major>1</rem:major>
<rem:minor>0</rem:minor>
<rem:date>
<rem:year>2018</rem:year>
<rem:month>8</rem:month>
<rem:day>22</rem:day>
</rem:date>
</rem:version>
<rem:authors stakeholders ="STK-0003 STK-0002 STK-0001 STK-0004 "/>
<rem:sources stakeholders ="STK-0002 "/>
<rem:comments>
Ninguno</rem:comments>
<rem:importance value = "IMV-0002"/>
<rem:urgency value = "URV-0002"/>
<rem:status value = "STV-0002"/>
<rem:stability value = "SBV-0004"/>
<rem:description>
Construir una línea de productos de software en el dominio del transporte terrestre de <rem:ref oid="GLO-0001">mercancía</rem:ref>.</rem:description>
<rem:objective
 oid = "OBJ-0002">
<rem:name>
Programar recogida</rem:name>
<rem:version>
<rem:major>1</rem:major>
<rem:minor>0</rem:minor>
<rem:date>
<rem:year>2018</rem:year>
<rem:month>9</rem:month>
<rem:day>4</rem:day>
</rem:date>
</rem:version>
<rem:authors stakeholders ="STK-0003 STK-0002 STK-0001 STK-0004 "/>
<rem:sources stakeholders ="STK-0002 "/>
<rem:comments>
Ninguno</rem:comments>
<rem:importance value = "IMV-0002"/>
<rem:urgency value = "URV-0002"/>
<rem:status value = "STV-0002"/>
<rem:stability>
<rem:tbd/>
</rem:stability>
<rem:description>
Construir una línea de productos que permita gestionar la información de las programaciones de recogida de <rem:ref oid="GLO-0001">mercancía</rem:ref>.</rem:description>
</rem:objective>
<rem:objective
 oid = "OBJ-0003">
<rem:name>
Recibir <rem:ref oid="GLO-0001">mercancía</rem:ref></rem:name>
<rem:version>
<rem:major>1</rem:major>
<rem:minor>0</rem:minor>
<rem:date>
<rem:year>2018</rem:year>
<rem:month>9</rem:month>
<rem:day>4</rem:day>
</rem:date>
</rem:version>
<rem:authors stakeholders ="STK-0003 STK-0002 STK-0001 STK-0004 "/>
<rem:sources stakeholders ="STK-0002 "/>
<rem:comments>
Ninguno</rem:comments>
<rem:importance value = "IMV-0002"/>
<rem:urgency value = "URV-0002"/>
<rem:status value = "STV-0002"/>
<rem:stability value = "SBV-0004"/>
<rem:description>
Construir una línea de productos que permita gestionar la información de los recibos de <rem:ref oid="GLO-0001">mercancía</rem:ref>.</rem:description>
</rem:objective>
<rem:objective
 oid = "OBJ-0004">
<rem:name>
Transportar <rem:ref oid="GLO-0001">mercancía</rem:ref></rem:name>
<rem:version>
<rem:major>1</rem:major>
<rem:minor>0</rem:minor>
<rem:date>
<rem:year>2018</rem:year>
<rem:month>9</rem:month>
<rem:day>4</rem:day>
</rem:date>
</rem:version>
<rem:authors stakeholders ="STK-0003 STK-0002 STK-0001 STK-0004 "/>
<rem:sources stakeholders ="STK-0002 "/>
<rem:comments>
Ninguno</rem:comments>
<rem:importance>
<rem:tbd/>
</rem:importance>
<rem:urgency>
<rem:tbd/>
</rem:urgency>
<rem:status>
<rem:tbd/>
</rem:status>
<rem:stability>
<rem:tbd/>
</rem:stability>
<rem:description>
Construir una línea de productos que permita gestionar la información del transporte de <rem:ref oid="GLO-0001">mercancía</rem:ref> desde el origen hasta el destino.</rem:description>
</rem:objective>
<rem:objective
 oid = "OBJ-0005">
<rem:name>
Entregar <rem:ref oid="GLO-0001">mercancía</rem:ref></rem:name>
<rem:version>
<rem:major>1</rem:major>
<rem:minor>0</rem:minor>
<rem:date>
<rem:year>2018</rem:year>
<rem:month>9</rem:month>
<rem:day>4</rem:day>
</rem:date>
</rem:version>
<rem:authors stakeholders ="STK-0003 STK-0002 STK-0001 STK-0004 "/>
<rem:sources stakeholders ="STK-0002 "/>
<rem:comments>
Ninguno</rem:comments>
<rem:importance value = "IMV-0002"/>
<rem:urgency value = "URV-0002"/>
<rem:status value = "STV-0002"/>
<rem:stability value = "SBV-0004"/>
<rem:description>
Construir un línea de productos que permita gestionar la información de las entregas de <rem:ref oid="GLO-0001">mercancía</rem:ref>.</rem:description>
</rem:objective>
<rem:objective
 oid = "OBJ-0006">
<rem:name>
Rastrear</rem:name>
<rem:version>
<rem:major>1</rem:major>
<rem:minor>0</rem:minor>
<rem:date>
<rem:year>2018</rem:year>
<rem:month>9</rem:month>
<rem:day>4</rem:day>
</rem:date>
</rem:version>
<rem:comments>
Ninguno</rem:comments>
<rem:importance>
<rem:tbd/>
</rem:importance>
<rem:urgency>
<rem:tbd/>
</rem:urgency>
<rem:status>
<rem:tbd/>
</rem:status>
<rem:stability>
<rem:tbd/>
</rem:stability>
<rem:description>
Construir un línea de productos que permita rastrear interna y externamente el proceso en el que se encuentra un envío de <rem:ref oid="GLO-0001">mercancía</rem:ref>.</rem:description>
</rem:objective>
</rem:objective>
</rem:section>
<rem:section
 oid = "SEC-0003">
<rem:name>
Requisitos</rem:name>
<rem:version>
<rem:major>1</rem:major>
<rem:minor>0</rem:minor>
<rem:date>
<rem:year>2018</rem:year>
<rem:month>8</rem:month>
<rem:day>21</rem:day>
</rem:date>
</rem:version>
<rem:comments>
Ninguno</rem:comments>
<rem:level>1</rem:level>
<rem:number>5 </rem:number>
<rem:section
 oid = "SEC-0007">
<rem:name>
Requisitos de información</rem:name>
<rem:version>
<rem:major>1</rem:major>
<rem:minor>0</rem:minor>
<rem:date>
<rem:year>2018</rem:year>
<rem:month>8</rem:month>
<rem:day>22</rem:day>
</rem:date>
</rem:version>
<rem:comments>
Ninguno</rem:comments>
<rem:level>2</rem:level>
<rem:number>5.1 </rem:number>
<rem:informationRequirement
 oid = "IRQ-0001">
<rem:name>
Programación servicio</rem:name>
<rem:version>
<rem:major>1</rem:major>
<rem:minor>0</rem:minor>
<rem:date>
<rem:year>2018</rem:year>
<rem:month>8</rem:month>
<rem:day>22</rem:day>
</rem:date>
</rem:version>
<rem:authors stakeholders ="STK-0003 STK-0002 STK-0001 STK-0004 "/>
<rem:sources stakeholders ="STK-0002 "/>
<rem:comments>
Ninguno</rem:comments>
<rem:importance value = "IMV-0002"/>
<rem:urgency value = "URV-0002"/>
<rem:status value = "STV-0002"/>
<rem:stability value = "SBV-0004"/>
<rem:relevantConcept>
la programación del servicio de recogida</rem:relevantConcept>
<rem:averageLifeTime>
<rem:value>5</rem:value>
<rem:timeUnit value = "TUV-0002"/>
</rem:averageLifeTime>
<rem:maximumLifeTime>
<rem:value>5</rem:value>
<rem:timeUnit value = "TUV-0002"/>
</rem:maximumLifeTime>
<rem:averageOcurrences><rem:value>1000</rem:value>
</rem:averageOcurrences>
<rem:maximumOcurrences><rem:value>1000</rem:value>
</rem:maximumOcurrences>
<rem:specificData oid = "DAT-0055">
<rem:description>
Código recogida</rem:description>
<rem:comments>
Identificador único de la programación</rem:comments>
</rem:specificData>
<rem:specificData oid = "DAT-0020">
<rem:description>
Código operador</rem:description>
<rem:comments>
</rem:comments>
</rem:specificData>
<rem:specificData oid = "DAT-0015">
<rem:description>
Fecha programación</rem:description>
<rem:comments>
Es la fecha en la que van a recoger la <rem:ref oid="GLO-0001">mercancía</rem:ref>.</rem:comments>
</rem:specificData>
<rem:specificData oid = "DAT-0076">
<rem:description>
Código <rem:ref oid="GLO-0007">tripulación</rem:ref></rem:description>
<rem:comments>
Ninguno</rem:comments>
</rem:specificData>
<rem:specificData oid = "DAT-0016">
<rem:description>
Fecha llamada</rem:description>
<rem:comments>
Fecha en la que el <rem:ref oid="GLO-0002">remitente</rem:ref> hace la llamada</rem:comments>
</rem:specificData>
<rem:specificData oid = "DAT-0001">
<rem:description>
Identificación <rem:ref oid="GLO-0002">remitente</rem:ref></rem:description>
<rem:comments>
Ninguno</rem:comments>
</rem:specificData>
<rem:specificData oid = "DAT-0002">
<rem:description>
Nombre <rem:ref oid="GLO-0002">remitente</rem:ref></rem:description>
<rem:comments>
Ninguno</rem:comments>
</rem:specificData>
<rem:specificData oid = "DAT-0003">
<rem:description>
Dirección <rem:ref oid="GLO-0002">remitente</rem:ref></rem:description>
<rem:comments>
Ninguno</rem:comments>
</rem:specificData>
<rem:specificData oid = "DAT-0018">
<rem:description>
Código DANE <rem:ref oid="GLO-0002">remitente</rem:ref></rem:description>
<rem:comments>
Ciudad asociada a la dirección de recogida.</rem:comments>
</rem:specificData>
<rem:specificData oid = "DAT-0004">
<rem:description>
Teléfonos <rem:ref oid="GLO-0002">remitente</rem:ref></rem:description>
<rem:comments>
Ninguno</rem:comments>
</rem:specificData>
<rem:specificData oid = "DAT-0006">
<rem:description>
Identificación <rem:ref oid="GLO-0003">destinatario</rem:ref></rem:description>
<rem:comments>
Ninguno</rem:comments>
</rem:specificData>
<rem:specificData oid = "DAT-0007">
<rem:description>
Nombre <rem:ref oid="GLO-0003">destinatario</rem:ref></rem:description>
<rem:comments>
Ninguno</rem:comments>
</rem:specificData>
<rem:specificData oid = "DAT-0008">
<rem:description>
Dirección <rem:ref oid="GLO-0003">destinatario</rem:ref></rem:description>
<rem:comments>
Ninguno</rem:comments>
</rem:specificData>
<rem:specificData oid = "DAT-0019">
<rem:description>
Código DANE <rem:ref oid="GLO-0003">destinatario</rem:ref></rem:description>
<rem:comments>
Ciudad asociada a la dirección de entrega.</rem:comments>
</rem:specificData>
<rem:specificData oid = "DAT-0009">
<rem:description>
Teléfonos <rem:ref oid="GLO-0003">destinatario</rem:ref></rem:description>
<rem:comments>
Ninguno</rem:comments>
</rem:specificData>
<rem:specificData oid = "DAT-0014">
<rem:description>
Token</rem:description>
<rem:comments>
Información de autenticación.</rem:comments>
</rem:specificData>
</rem:informationRequirement>
<rem:informationRequirement
 oid = "IRQ-0002">
<rem:name>
Recibo de <rem:ref oid="GLO-0001">mercancía</rem:ref></rem:name>
<rem:version>
<rem:major>1</rem:major>
<rem:minor>0</rem:minor>
<rem:date>
<rem:year>2018</rem:year>
<rem:month>8</rem:month>
<rem:day>22</rem:day>
</rem:date>
</rem:version>
<rem:authors stakeholders ="STK-0003 STK-0002 STK-0001 STK-0004 "/>
<rem:sources stakeholders ="STK-0002 "/>
<rem:comments>
Ninguno</rem:comments>
<rem:importance value = "IMV-0002"/>
<rem:urgency value = "URV-0002"/>
<rem:status value = "STV-0002"/>
<rem:stability value = "SBV-0004"/>
<rem:relevantConcept>
la programación de recogida</rem:relevantConcept>
<rem:averageLifeTime>
<rem:value>5</rem:value>
<rem:timeUnit value = "TUV-0002"/>
</rem:averageLifeTime>
<rem:maximumLifeTime>
<rem:value>5</rem:value>
<rem:timeUnit value = "TUV-0002"/>
</rem:maximumLifeTime>
<rem:averageOcurrences><rem:value>1000</rem:value>
</rem:averageOcurrences>
<rem:maximumOcurrences><rem:value>1000</rem:value>
</rem:maximumOcurrences>
<rem:specificData oid = "DAT-0056">
<rem:description>
Código remisión</rem:description>
<rem:comments>
Identificador único del recibo.</rem:comments>
</rem:specificData>
<rem:specificData oid = "DAT-0031">
<rem:description>
Código operador</rem:description>
<rem:comments>
Ninguno</rem:comments>
</rem:specificData>
<rem:specificData oid = "DAT-0005">
<rem:description>
Código recogida</rem:description>
<rem:comments>
Identificación de la programación de recogida asociada.</rem:comments>
</rem:specificData>
<rem:specificData oid = "DAT-0029">
<rem:description>
Código <rem:ref oid="GLO-0007">tripulación</rem:ref></rem:description>
<rem:comments>
Ninguno</rem:comments>
</rem:specificData>
<rem:specificData oid = "DAT-0022">
<rem:description>
Peso</rem:description>
<rem:comments>
Ninguno</rem:comments>
</rem:specificData>
<rem:specificData oid = "DAT-0023">
<rem:description>
Volumen</rem:description>
<rem:comments>
Ninguno</rem:comments>
</rem:specificData>
<rem:specificData oid = "DAT-0024">
<rem:description>
Valor flete</rem:description>
<rem:comments>
Ninguno</rem:comments>
</rem:specificData>
<rem:specificData oid = "DAT-0030">
<rem:description>
Fecha recogida</rem:description>
<rem:comments>
Ninguno</rem:comments>
</rem:specificData>
<rem:specificData oid = "DAT-0035">
<rem:description>
Tipo recogida</rem:description>
<rem:comments>
<rem:ref oid="GLO-0006">Base</rem:ref>, <rem:ref oid="GLO-0004">Ventanilla</rem:ref>, Dirección origen</rem:comments>
</rem:specificData>
<rem:specificData oid = "DAT-0080">
<rem:description>
Tipo entrega</rem:description>
<rem:comments>
<rem:ref oid="GLO-0006">Base</rem:ref>, <rem:ref oid="GLO-0004">Ventanilla</rem:ref>, Dirección destino</rem:comments>
</rem:specificData>
<rem:specificData oid = "DAT-0039">
<rem:description>
Numero unidades</rem:description>
<rem:comments>
Ninguno</rem:comments>
</rem:specificData>
<rem:specificData oid = "DAT-0050">
<rem:description>
Token</rem:description>
<rem:comments>
Ninguno</rem:comments>
</rem:specificData>
</rem:informationRequirement>
<rem:informationRequirement
 oid = "IRQ-0003">
<rem:name>
Transporte</rem:name>
<rem:version>
<rem:major>1</rem:major>
<rem:minor>0</rem:minor>
<rem:date>
<rem:year>2018</rem:year>
<rem:month>8</rem:month>
<rem:day>22</rem:day>
</rem:date>
</rem:version>
<rem:authors stakeholders ="STK-0003 STK-0002 STK-0001 STK-0004 "/>
<rem:sources stakeholders ="STK-0002 "/>
<rem:comments>
Ninguno</rem:comments>
<rem:importance value = "IMV-0002"/>
<rem:urgency value = "URV-0002"/>
<rem:status value = "STV-0002"/>
<rem:stability value = "SBV-0004"/>
<rem:relevantConcept>
la programación de recogida</rem:relevantConcept>
<rem:averageLifeTime>
<rem:value>5</rem:value>
<rem:timeUnit value = "TUV-0002"/>
</rem:averageLifeTime>
<rem:maximumLifeTime>
<rem:value>5</rem:value>
<rem:timeUnit value = "TUV-0002"/>
</rem:maximumLifeTime>
<rem:averageOcurrences><rem:value>1000</rem:value>
</rem:averageOcurrences>
<rem:maximumOcurrences><rem:value>1000</rem:value>
</rem:maximumOcurrences>
<rem:specificData oid = "DAT-0057">
<rem:description>
Código transporte</rem:description>
<rem:comments>
Identificador único del transporte.</rem:comments>
</rem:specificData>
<rem:specificData oid = "DAT-0036">
<rem:description>
Código operador<br/></rem:description>
<rem:comments>
Ninguno</rem:comments>
</rem:specificData>
<rem:specificData oid = "DAT-0010">
<rem:description>
Código remisión</rem:description>
<rem:comments>
Identificador del recibo de <rem:ref oid="GLO-0001">mercancía</rem:ref> asociado.</rem:comments>
</rem:specificData>
<rem:specificData oid = "DAT-0054">
<rem:description>
Código <rem:ref oid="GLO-0007">tripulación</rem:ref></rem:description>
<rem:comments>
Ninguno</rem:comments>
</rem:specificData>
<rem:specificData oid = "DAT-0051">
<rem:description>
Token</rem:description>
<rem:comments>
Ninguno</rem:comments>
</rem:specificData>
<rem:specificData oid = "DAT-0052">
<rem:description>
Fecha inicio</rem:description>
<rem:comments>
Ninguno</rem:comments>
</rem:specificData>
<rem:specificData oid = "DAT-0053">
<rem:description>
Fecha fin</rem:description>
<rem:comments>
Ninguno</rem:comments>
</rem:specificData>
<rem:specificData oid = "DAT-0068">
<rem:description>
Tipo</rem:description>
<rem:comments>
Origen, Destino</rem:comments>
</rem:specificData>
</rem:informationRequirement>
<rem:informationRequirement
 oid = "IRQ-0004">
<rem:name>
Entrega</rem:name>
<rem:version>
<rem:major>1</rem:major>
<rem:minor>0</rem:minor>
<rem:date>
<rem:year>2018</rem:year>
<rem:month>8</rem:month>
<rem:day>22</rem:day>
</rem:date>
</rem:version>
<rem:authors stakeholders ="STK-0003 STK-0002 STK-0001 STK-0004 "/>
<rem:sources stakeholders ="STK-0002 "/>
<rem:comments>
Ninguno</rem:comments>
<rem:importance value = "IMV-0002"/>
<rem:urgency value = "URV-0002"/>
<rem:status value = "STV-0002"/>
<rem:stability value = "SBV-0004"/>
<rem:relevantConcept>
la programación de recogida</rem:relevantConcept>
<rem:averageLifeTime>
<rem:value>5</rem:value>
<rem:timeUnit value = "TUV-0002"/>
</rem:averageLifeTime>
<rem:maximumLifeTime>
<rem:value>5</rem:value>
<rem:timeUnit value = "TUV-0002"/>
</rem:maximumLifeTime>
<rem:averageOcurrences><rem:value>1000</rem:value>
</rem:averageOcurrences>
<rem:maximumOcurrences><rem:value>1000</rem:value>
</rem:maximumOcurrences>
<rem:specificData oid = "DAT-0067">
<rem:description>
Código entrega</rem:description>
<rem:comments>
Identificador único de la entrega</rem:comments>
</rem:specificData>
<rem:specificData oid = "DAT-0072">
<rem:description>
Código operador</rem:description>
<rem:comments>
Ninguno</rem:comments>
</rem:specificData>
<rem:specificData oid = "DAT-0011">
<rem:description>
Código remisión</rem:description>
<rem:comments>
Ninguno</rem:comments>
</rem:specificData>
<rem:specificData oid = "DAT-0065">
<rem:description>
Código <rem:ref oid="GLO-0007">tripulación</rem:ref></rem:description>
<rem:comments>
Ninguno</rem:comments>
</rem:specificData>
<rem:specificData oid = "DAT-0066">
<rem:description>
Fecha entrega</rem:description>
<rem:comments>
Ninguno</rem:comments>
</rem:specificData>
<rem:specificData oid = "DAT-0069">
<rem:description>
Tipo entrega</rem:description>
<rem:comments>
Ventilla, Dirección destino, <rem:ref oid="GLO-0006">Base</rem:ref></rem:comments>
</rem:specificData>
<rem:specificData oid = "DAT-0083">
<rem:description>
Porcentaje flete</rem:description>
<rem:comments>
porcentaje flete aplicado si es en destino, <rem:ref oid="GLO-0004">ventanilla</rem:ref> o <rem:ref oid="GLO-0006">base</rem:ref></rem:comments>
</rem:specificData>
</rem:informationRequirement>
<rem:informationRequirement
 oid = "IRQ-0005">
<rem:name>
Rastreo</rem:name>
<rem:version>
<rem:major>1</rem:major>
<rem:minor>0</rem:minor>
<rem:date>
<rem:year>2018</rem:year>
<rem:month>8</rem:month>
<rem:day>22</rem:day>
</rem:date>
</rem:version>
<rem:authors stakeholders ="STK-0003 STK-0002 STK-0001 STK-0004 "/>
<rem:sources stakeholders ="STK-0002 "/>
<rem:comments>
Ninguno</rem:comments>
<rem:importance value = "IMV-0002"/>
<rem:urgency value = "URV-0002"/>
<rem:status value = "STV-0002"/>
<rem:stability value = "SBV-0004"/>
<rem:relevantConcept>
lugar y proceso del trámite</rem:relevantConcept>
<rem:averageLifeTime>
<rem:value>5</rem:value>
<rem:timeUnit value = "TUV-0002"/>
</rem:averageLifeTime>
<rem:maximumLifeTime>
<rem:value>5</rem:value>
<rem:timeUnit value = "TUV-0002"/>
</rem:maximumLifeTime>
<rem:averageOcurrences><rem:value>1000</rem:value>
</rem:averageOcurrences>
<rem:maximumOcurrences><rem:value>1000</rem:value>
</rem:maximumOcurrences>
<rem:specificData oid = "DAT-0012">
<rem:description>
Código rastreo</rem:description>
<rem:comments>
Identificador único del rastro.</rem:comments>
</rem:specificData>
<rem:specificData oid = "DAT-0073">
<rem:description>
Subproceso</rem:description>
<rem:comments>
Recibo, Entrega, Transporte, Transporte origen, Transporte destino</rem:comments>
</rem:specificData>
<rem:specificData oid = "DAT-0074">
<rem:description>
Fecha</rem:description>
<rem:comments>
Ninguno</rem:comments>
</rem:specificData>
<rem:specificData oid = "DAT-0075">
<rem:description>
Tipo</rem:description>
<rem:comments>
Externo, Interno, Interno-Externo</rem:comments>
</rem:specificData>
</rem:informationRequirement>
<rem:informationRequirement
 oid = "IRQ-0008">
<rem:name>
<rem:ref oid="GLO-0007">Tripulación</rem:ref></rem:name>
<rem:version>
<rem:major>1</rem:major>
<rem:minor>0</rem:minor>
<rem:date>
<rem:year>2018</rem:year>
<rem:month>8</rem:month>
<rem:day>31</rem:day>
</rem:date>
</rem:version>
<rem:authors stakeholders ="STK-0003 STK-0002 STK-0001 STK-0004 "/>
<rem:sources stakeholders ="STK-0002 "/>
<rem:comments>
Ninguno</rem:comments>
<rem:importance value = "IMV-0002"/>
<rem:urgency value = "URV-0002"/>
<rem:status value = "STV-0002"/>
<rem:stability value = "SBV-0004"/>
<rem:relevantConcept>
el tripulante</rem:relevantConcept>
<rem:averageLifeTime>
<rem:value>5</rem:value>
<rem:timeUnit value = "TUV-0002"/>
</rem:averageLifeTime>
<rem:maximumLifeTime>
<rem:value>5</rem:value>
<rem:timeUnit value = "TUV-0002"/>
</rem:maximumLifeTime>
<rem:averageOcurrences><rem:value>10</rem:value>
</rem:averageOcurrences>
<rem:maximumOcurrences><rem:value>100</rem:value>
</rem:maximumOcurrences>
<rem:specificData oid = "DAT-0032">
<rem:description>
Código <rem:ref oid="GLO-0007">tripulación</rem:ref></rem:description>
<rem:comments>
Ninguno</rem:comments>
</rem:specificData>
<rem:specificData oid = "DAT-0071">
<rem:description>
Código operador</rem:description>
<rem:comments>
Ninguno</rem:comments>
</rem:specificData>
<rem:specificData oid = "DAT-0077">
<rem:description>
Identificación</rem:description>
<rem:comments>
Ninguno</rem:comments>
</rem:specificData>
<rem:specificData oid = "DAT-0034">
<rem:description>
Nombre</rem:description>
<rem:comments>
Ninguno</rem:comments>
</rem:specificData>
</rem:informationRequirement>
</rem:section>
<rem:section
 oid = "SEC-0004">
<rem:name>
Requisitos funcionales</rem:name>
<rem:version>
<rem:major>1</rem:major>
<rem:minor>0</rem:minor>
<rem:date>
<rem:year>2018</rem:year>
<rem:month>8</rem:month>
<rem:day>21</rem:day>
</rem:date>
</rem:version>
<rem:comments>
Ninguno</rem:comments>
<rem:level>2</rem:level>
<rem:number>5.2 </rem:number>
<rem:functionalRequirement
 oid = "FRQ-0001">
<rem:name>
Programar servicio</rem:name>
<rem:version>
<rem:major>1</rem:major>
<rem:minor>0</rem:minor>
<rem:date>
<rem:year>2018</rem:year>
<rem:month>8</rem:month>
<rem:day>21</rem:day>
</rem:date>
</rem:version>
<rem:authors stakeholders ="STK-0003 STK-0002 STK-0001 STK-0004 "/>
<rem:sources stakeholders ="STK-0002 "/>
<rem:comments>
Ninguno</rem:comments>
<rem:importance value = "IMV-0002"/>
<rem:urgency value = "URV-0002"/>
<rem:status value = "STV-0002"/>
<rem:stability value = "SBV-0004"/>
<rem:description>
permitir programar el servicio de recogida de <rem:ref oid="GLO-0001">mercancía</rem:ref> solicitada por un <rem:ref oid="GLO-0002">remitente</rem:ref> a través de una API.<br/>Debe almacenar información requerida en IRQ-0001.</rem:description>
</rem:functionalRequirement>
<rem:functionalRequirement
 oid = "FRQ-0002">
<rem:name>
Recibo de <rem:ref oid="GLO-0001">mercancía</rem:ref></rem:name>
<rem:version>
<rem:major>1</rem:major>
<rem:minor>0</rem:minor>
<rem:date>
<rem:year>2018</rem:year>
<rem:month>8</rem:month>
<rem:day>21</rem:day>
</rem:date>
</rem:version>
<rem:authors stakeholders ="STK-0003 STK-0002 STK-0001 STK-0004 "/>
<rem:sources stakeholders ="STK-0002 "/>
<rem:comments>
Ninguno</rem:comments>
<rem:importance value = "IMV-0002"/>
<rem:urgency value = "URV-0002"/>
<rem:status value = "STV-0002"/>
<rem:stability value = "SBV-0004"/>
<rem:description>
permitir guardar la información del recibo de <rem:ref oid="GLO-0001">mercancía</rem:ref> a través de una API.<br/>Debe almacenar la información requerida en IRQ-0002.</rem:description>
</rem:functionalRequirement>
<rem:functionalRequirement
 oid = "FRQ-0007">
<rem:name>
Recibo de <rem:ref oid="GLO-0001">mercancía</rem:ref> (Dirección origen)</rem:name>
<rem:version>
<rem:major>1</rem:major>
<rem:minor>0</rem:minor>
<rem:date>
<rem:year>2018</rem:year>
<rem:month>8</rem:month>
<rem:day>27</rem:day>
</rem:date>
</rem:version>
<rem:authors stakeholders ="STK-0003 STK-0002 STK-0001 STK-0004 "/>
<rem:sources stakeholders ="STK-0002 "/>
<rem:comments>
Ninguno</rem:comments>
<rem:importance value = "IMV-0002"/>
<rem:urgency value = "URV-0002"/>
<rem:status value = "STV-0002"/>
<rem:stability value = "SBV-0004"/>
<rem:description>
permitir guardar la información del recibo de <rem:ref oid="GLO-0001">mercancía</rem:ref> en <rem:ref oid="GLO-0005">dirección de origen</rem:ref> a través de una API.<br/>Debe almacenar la información requerida en IRQ-0002.</rem:description>
</rem:functionalRequirement>
<rem:functionalRequirement
 oid = "FRQ-0008">
<rem:name>
Recibo de <rem:ref oid="GLO-0001">mercancía</rem:ref> (<rem:ref oid="GLO-0004">Ventanilla</rem:ref>)</rem:name>
<rem:version>
<rem:major>1</rem:major>
<rem:minor>0</rem:minor>
<rem:date>
<rem:year>2018</rem:year>
<rem:month>8</rem:month>
<rem:day>27</rem:day>
</rem:date>
</rem:version>
<rem:authors stakeholders ="STK-0003 STK-0002 STK-0001 STK-0004 "/>
<rem:sources stakeholders ="STK-0002 "/>
<rem:comments>
Ninguno</rem:comments>
<rem:importance value = "IMV-0002"/>
<rem:urgency value = "URV-0002"/>
<rem:status value = "STV-0002"/>
<rem:stability value = "SBV-0004"/>
<rem:description>
permitir guardar la información del recibo de <rem:ref oid="GLO-0001">mercancía</rem:ref> por <rem:ref oid="GLO-0004">ventanilla</rem:ref> a través de una API.<br/>Debe almacenar la información requerida en IRQ-0002.</rem:description>
</rem:functionalRequirement>
<rem:functionalRequirement
 oid = "FRQ-0009">
<rem:name>
Recibo de <rem:ref oid="GLO-0001">mercancía</rem:ref> (<rem:ref oid="GLO-0006">Base</rem:ref>)</rem:name>
<rem:version>
<rem:major>1</rem:major>
<rem:minor>0</rem:minor>
<rem:date>
<rem:year>2018</rem:year>
<rem:month>8</rem:month>
<rem:day>27</rem:day>
</rem:date>
</rem:version>
<rem:authors stakeholders ="STK-0003 STK-0002 STK-0001 STK-0004 "/>
<rem:sources stakeholders ="STK-0002 "/>
<rem:comments>
Ninguno</rem:comments>
<rem:importance value = "IMV-0002"/>
<rem:urgency value = "URV-0002"/>
<rem:status value = "STV-0002"/>
<rem:stability value = "SBV-0004"/>
<rem:description>
permitir guardar la información del recibo de <rem:ref oid="GLO-0001">mercancía</rem:ref> en <rem:ref oid="GLO-0006">base</rem:ref> a través de una API.<br/>Debe almacenar la información requerida en IRQ-0002.</rem:description>
</rem:functionalRequirement>
<rem:functionalRequirement
 oid = "FRQ-0003">
<rem:name>
Transporte <rem:ref oid="GLO-0001">mercancía</rem:ref></rem:name>
<rem:version>
<rem:major>1</rem:major>
<rem:minor>0</rem:minor>
<rem:date>
<rem:year>2018</rem:year>
<rem:month>8</rem:month>
<rem:day>21</rem:day>
</rem:date>
</rem:version>
<rem:authors stakeholders ="STK-0003 STK-0002 STK-0001 STK-0004 "/>
<rem:sources stakeholders ="STK-0002 "/>
<rem:comments>
Ninguno</rem:comments>
<rem:importance value = "IMV-0002"/>
<rem:urgency value = "URV-0002"/>
<rem:status value = "STV-0002"/>
<rem:stability value = "SBV-0004"/>
<rem:description>
debería permitir almacenar la información del transporte de la <rem:ref oid="GLO-0001">mercancía</rem:ref> a través de una API.</rem:description>
</rem:functionalRequirement>
<rem:functionalRequirement
 oid = "FRQ-0010">
<rem:name>
Transporte dirección recibo</rem:name>
<rem:version>
<rem:major>1</rem:major>
<rem:minor>0</rem:minor>
<rem:date>
<rem:year>2018</rem:year>
<rem:month>8</rem:month>
<rem:day>29</rem:day>
</rem:date>
</rem:version>
<rem:authors stakeholders ="STK-0003 STK-0002 STK-0001 STK-0004 "/>
<rem:sources stakeholders ="STK-0002 "/>
<rem:comments>
Ninguno</rem:comments>
<rem:importance value = "IMV-0002"/>
<rem:urgency value = "URV-0002"/>
<rem:status value = "STV-0002"/>
<rem:stability value = "SBV-0004"/>
<rem:description>
debería permitir almacenar la información del transporte de la <rem:ref oid="GLO-0001">mercancía</rem:ref> en caso de ser necesario desde el lugar de recogida hasta la central a través de una API.<br/>Debe almacenar la información requerida en IRQ-0003.</rem:description>
</rem:functionalRequirement>
<rem:functionalRequirement
 oid = "FRQ-0012">
<rem:name>
Transporte dirección entrega</rem:name>
<rem:version>
<rem:major>1</rem:major>
<rem:minor>0</rem:minor>
<rem:date>
<rem:year>2018</rem:year>
<rem:month>8</rem:month>
<rem:day>29</rem:day>
</rem:date>
</rem:version>
<rem:authors stakeholders ="STK-0003 STK-0002 STK-0001 STK-0004 "/>
<rem:sources stakeholders ="STK-0002 "/>
<rem:comments>
Ninguno</rem:comments>
<rem:importance value = "IMV-0002"/>
<rem:urgency value = "URV-0002"/>
<rem:status value = "STV-0002"/>
<rem:stability value = "SBV-0004"/>
<rem:description>
debería almacenar la información del transporte de la <rem:ref oid="GLO-0001">mercancía</rem:ref> en caso de ser necesario desde la central hasta el lugar de entrega  a través de una API.<br/>Debe almacenar la información requerida en IRQ-0003.</rem:description>
</rem:functionalRequirement>
<rem:functionalRequirement
 oid = "FRQ-0004">
<rem:name>
Entrega</rem:name>
<rem:version>
<rem:major>1</rem:major>
<rem:minor>0</rem:minor>
<rem:date>
<rem:year>2018</rem:year>
<rem:month>8</rem:month>
<rem:day>21</rem:day>
</rem:date>
</rem:version>
<rem:authors stakeholders ="STK-0003 STK-0002 STK-0001 STK-0004 "/>
<rem:sources stakeholders ="STK-0002 "/>
<rem:comments>
Ninguno</rem:comments>
<rem:importance value = "IMV-0002"/>
<rem:urgency value = "URV-0002"/>
<rem:status value = "STV-0002"/>
<rem:stability value = "SBV-0004"/>
<rem:description>
guardar la información de la entrega de la <rem:ref oid="GLO-0001">mercancía</rem:ref> al <rem:ref oid="GLO-0003">destinatario</rem:ref> a través de una API.<br/>Debe almacerar la información requerida en IRQ-0004.</rem:description>
</rem:functionalRequirement>
<rem:functionalRequirement
 oid = "FRQ-0015">
<rem:name>
Entrega (Dirección destino)</rem:name>
<rem:version>
<rem:major>1</rem:major>
<rem:minor>0</rem:minor>
<rem:date>
<rem:year>2018</rem:year>
<rem:month>8</rem:month>
<rem:day>29</rem:day>
</rem:date>
</rem:version>
<rem:authors stakeholders ="STK-0003 STK-0002 STK-0001 STK-0004 "/>
<rem:sources stakeholders ="STK-0002 "/>
<rem:comments>
Ninguno</rem:comments>
<rem:importance value = "IMV-0002"/>
<rem:urgency value = "URV-0002"/>
<rem:status value = "STV-0002"/>
<rem:stability value = "SBV-0004"/>
<rem:description>
guardar la información de la entrega en dirección destino de la <rem:ref oid="GLO-0001">mercancía</rem:ref> al <rem:ref oid="GLO-0003">destinatario</rem:ref> a través de una API.<br/>Debe almacenar la información requerida en IRQ-0004.</rem:description>
</rem:functionalRequirement>
<rem:functionalRequirement
 oid = "FRQ-0016">
<rem:name>
Entrega (<rem:ref oid="GLO-0006">Base</rem:ref>)</rem:name>
<rem:version>
<rem:major>1</rem:major>
<rem:minor>0</rem:minor>
<rem:date>
<rem:year>2018</rem:year>
<rem:month>8</rem:month>
<rem:day>29</rem:day>
</rem:date>
</rem:version>
<rem:authors stakeholders ="STK-0003 STK-0002 STK-0001 STK-0004 "/>
<rem:sources stakeholders ="STK-0002 "/>
<rem:comments>
Ninguno</rem:comments>
<rem:importance value = "IMV-0002"/>
<rem:urgency value = "URV-0002"/>
<rem:status value = "STV-0002"/>
<rem:stability value = "SBV-0004"/>
<rem:description>
guardar la información de la entrega en <rem:ref oid="GLO-0006">base</rem:ref> de la <rem:ref oid="GLO-0001">mercancía</rem:ref> al <rem:ref oid="GLO-0003">destinatario</rem:ref> a través de una API<br/>Debe almacenar la información requerida en IRQ-0004.</rem:description>
</rem:functionalRequirement>
<rem:functionalRequirement
 oid = "FRQ-0017">
<rem:name>
Entrega (<rem:ref oid="GLO-0004">Ventanilla</rem:ref>)</rem:name>
<rem:version>
<rem:major>1</rem:major>
<rem:minor>0</rem:minor>
<rem:date>
<rem:year>2018</rem:year>
<rem:month>8</rem:month>
<rem:day>29</rem:day>
</rem:date>
</rem:version>
<rem:authors stakeholders ="STK-0003 STK-0002 STK-0001 STK-0004 "/>
<rem:sources stakeholders ="STK-0002 "/>
<rem:comments>
Ninguno</rem:comments>
<rem:importance value = "IMV-0002"/>
<rem:urgency value = "URV-0002"/>
<rem:status value = "STV-0002"/>
<rem:stability value = "SBV-0004"/>
<rem:description>
guardar la información de la entrega en <rem:ref oid="GLO-0004">ventanilla</rem:ref> de la <rem:ref oid="GLO-0001">mercancía</rem:ref> al <rem:ref oid="GLO-0003">destinatario</rem:ref> a través de una API.<br/>Debe almacenar la información requerida en IRQ-0004.</rem:description>
</rem:functionalRequirement>
<rem:functionalRequirement
 oid = "FRQ-0005">
<rem:name>
Rastreo</rem:name>
<rem:version>
<rem:major>1</rem:major>
<rem:minor>0</rem:minor>
<rem:date>
<rem:year>2018</rem:year>
<rem:month>8</rem:month>
<rem:day>21</rem:day>
</rem:date>
</rem:version>
<rem:authors stakeholders ="STK-0003 STK-0002 STK-0001 STK-0004 "/>
<rem:sources stakeholders ="STK-0002 "/>
<rem:comments>
Proceso, fecha y tripulante<br/></rem:comments>
<rem:importance value = "IMV-0002"/>
<rem:urgency value = "URV-0002"/>
<rem:status value = "STV-0002"/>
<rem:stability value = "SBV-0004"/>
<rem:description>
debería realizar un rastreo con la información en IRQ-0005 a todo el proceso de envío y recibo de <rem:ref oid="GLO-0001">mercancía</rem:ref> para saber en que proceso se encuentra un trámite.</rem:description>
</rem:functionalRequirement>
<rem:functionalRequirement
 oid = "FRQ-0018">
<rem:name>
Rastreo externo</rem:name>
<rem:version>
<rem:major>1</rem:major>
<rem:minor>0</rem:minor>
<rem:date>
<rem:year>2018</rem:year>
<rem:month>8</rem:month>
<rem:day>29</rem:day>
</rem:date>
</rem:version>
<rem:authors stakeholders ="STK-0003 STK-0002 STK-0001 STK-0004 "/>
<rem:sources stakeholders ="STK-0002 "/>
<rem:comments>
Ninguno</rem:comments>
<rem:importance value = "IMV-0002"/>
<rem:urgency value = "URV-0002"/>
<rem:status value = "STV-0002"/>
<rem:stability value = "SBV-0004"/>
<rem:description>
debería realizar un rastreo dirigido al <rem:ref oid="GLO-0002">remitente</rem:ref> y <rem:ref oid="GLO-0003">destinatario</rem:ref> con la información en IRQ-0005 a todo el proceso de envío y entrega de <rem:ref oid="GLO-0001">mercancía</rem:ref> para que puedan saber en que proceso se encuentra su trámite.</rem:description>
</rem:functionalRequirement>
<rem:functionalRequirement
 oid = "FRQ-0019">
<rem:name>
Rastreo interno</rem:name>
<rem:version>
<rem:major>1</rem:major>
<rem:minor>0</rem:minor>
<rem:date>
<rem:year>2018</rem:year>
<rem:month>8</rem:month>
<rem:day>29</rem:day>
</rem:date>
</rem:version>
<rem:authors stakeholders ="STK-0003 STK-0002 STK-0001 STK-0004 "/>
<rem:sources stakeholders ="STK-0002 "/>
<rem:comments>
Ninguno</rem:comments>
<rem:importance value = "IMV-0002"/>
<rem:urgency value = "URV-0002"/>
<rem:status value = "STV-0002"/>
<rem:stability value = "SBV-0004"/>
<rem:description>
debería realizar un rastreo dirigido a área logística o interesados internos con la información en IRQ-0005 a todo el proceso de envío y entrega de <rem:ref oid="GLO-0001">mercancía</rem:ref> para que puedan saber en que lugar proceso se encuentra un trámite.</rem:description>
</rem:functionalRequirement>
<rem:functionalRequirement
 oid = "FRQ-0020">
<rem:name>
Consultar programaciones de servicios</rem:name>
<rem:version>
<rem:major>1</rem:major>
<rem:minor>0</rem:minor>
<rem:date>
<rem:year>2018</rem:year>
<rem:month>9</rem:month>
<rem:day>2</rem:day>
</rem:date>
</rem:version>
<rem:authors stakeholders ="STK-0003 STK-0002 STK-0001 STK-0004 "/>
<rem:sources stakeholders ="STK-0002 "/>
<rem:comments>
Ninguno</rem:comments>
<rem:importance value = "IMV-0002"/>
<rem:urgency value = "URV-0002"/>
<rem:status value = "STV-0002"/>
<rem:stability value = "SBV-0004"/>
<rem:description>
permitir consultar las programaciones de servicios de recogida de <rem:ref oid="GLO-0001">mercancía</rem:ref> a través de una API.<br/>Debe consultar información requerida en IRQ-0001.</rem:description>
</rem:functionalRequirement>
<rem:functionalRequirement
 oid = "FRQ-0021">
<rem:name>
Consultar recibos de <rem:ref oid="GLO-0001">mercancía</rem:ref></rem:name>
<rem:version>
<rem:major>1</rem:major>
<rem:minor>0</rem:minor>
<rem:date>
<rem:year>2018</rem:year>
<rem:month>9</rem:month>
<rem:day>2</rem:day>
</rem:date>
</rem:version>
<rem:authors stakeholders ="STK-0003 STK-0002 STK-0001 STK-0004 "/>
<rem:sources stakeholders ="STK-0002 "/>
<rem:comments>
Ninguno</rem:comments>
<rem:importance value = "IMV-0002"/>
<rem:urgency value = "URV-0002"/>
<rem:status value = "STV-0002"/>
<rem:stability value = "SBV-0004"/>
<rem:description>
permitir consultar los recibos de <rem:ref oid="GLO-0001">mercancía</rem:ref> a través de una API.<br/>Debe consultar información requerida en IRQ-0002.</rem:description>
</rem:functionalRequirement>
<rem:functionalRequirement
 oid = "FRQ-0022">
<rem:name>
Consultar transportes de <rem:ref oid="GLO-0001">mercancía</rem:ref> origen</rem:name>
<rem:version>
<rem:major>1</rem:major>
<rem:minor>0</rem:minor>
<rem:date>
<rem:year>2018</rem:year>
<rem:month>9</rem:month>
<rem:day>2</rem:day>
</rem:date>
</rem:version>
<rem:authors stakeholders ="STK-0003 STK-0002 STK-0001 STK-0004 "/>
<rem:sources stakeholders ="STK-0002 "/>
<rem:comments>
Ninguno</rem:comments>
<rem:importance value = "IMV-0002"/>
<rem:urgency value = "URV-0002"/>
<rem:status value = "STV-0002"/>
<rem:stability value = "SBV-0004"/>
<rem:description>
permitir consultar los transportes de <rem:ref oid="GLO-0001">mercancía</rem:ref> desde el sitio de recibo hasta la central a través de una API.<br/>Debe consultar información requerida en IRQ-0003.</rem:description>
</rem:functionalRequirement>
<rem:functionalRequirement
 oid = "FRQ-0023">
<rem:name>
Consultar transportes de <rem:ref oid="GLO-0001">mercancía</rem:ref> destino</rem:name>
<rem:version>
<rem:major>1</rem:major>
<rem:minor>0</rem:minor>
<rem:date>
<rem:year>2018</rem:year>
<rem:month>9</rem:month>
<rem:day>2</rem:day>
</rem:date>
</rem:version>
<rem:authors stakeholders ="STK-0003 STK-0002 STK-0001 STK-0004 "/>
<rem:sources stakeholders ="STK-0002 "/>
<rem:comments>
Ninguno</rem:comments>
<rem:importance value = "IMV-0002"/>
<rem:urgency value = "URV-0002"/>
<rem:status value = "STV-0002"/>
<rem:stability value = "SBV-0004"/>
<rem:description>
permitir consultar los transportes de <rem:ref oid="GLO-0001">mercancía</rem:ref> desde la central hasta el sitio de entrega a través de una API.<br/>Debe consultar información requerida en IRQ-0003.</rem:description>
</rem:functionalRequirement>
<rem:functionalRequirement
 oid = "FRQ-0024">
<rem:name>
Consultar entregas de <rem:ref oid="GLO-0001">mercancía</rem:ref></rem:name>
<rem:version>
<rem:major>1</rem:major>
<rem:minor>0</rem:minor>
<rem:date>
<rem:year>2018</rem:year>
<rem:month>9</rem:month>
<rem:day>2</rem:day>
</rem:date>
</rem:version>
<rem:authors stakeholders ="STK-0003 STK-0002 STK-0001 STK-0004 "/>
<rem:sources stakeholders ="STK-0002 "/>
<rem:comments>
Ninguno</rem:comments>
<rem:importance value = "IMV-0002"/>
<rem:urgency value = "URV-0002"/>
<rem:status value = "STV-0002"/>
<rem:stability value = "SBV-0004"/>
<rem:description>
permitir consultar las entregas de <rem:ref oid="GLO-0001">mercancía</rem:ref> a través de una API.<br/>Debe consultar información requerida en IRQ-0004.</rem:description>
</rem:functionalRequirement>
</rem:section>
<rem:section
 oid = "SEC-0008">
<rem:name>
Requisitos no funcionales</rem:name>
<rem:version>
<rem:major>1</rem:major>
<rem:minor>0</rem:minor>
<rem:date>
<rem:year>2018</rem:year>
<rem:month>8</rem:month>
<rem:day>22</rem:day>
</rem:date>
</rem:version>
<rem:comments>
Ninguno</rem:comments>
<rem:level>2</rem:level>
<rem:number>5.3 </rem:number>
<rem:section
 oid = "SEC-0012">
<rem:name>
Compatibilidad</rem:name>
<rem:version>
<rem:major>1</rem:major>
<rem:minor>0</rem:minor>
<rem:date>
<rem:year>2018</rem:year>
<rem:month>8</rem:month>
<rem:day>29</rem:day>
</rem:date>
</rem:version>
<rem:comments>
Ninguno</rem:comments>
<rem:level>3</rem:level>
<rem:number>5.3.1 </rem:number>
<rem:nonFunctionalRequirement
 oid = "NFR-0001">
<rem:name>
Interoperabilidad</rem:name>
<rem:version>
<rem:major>1</rem:major>
<rem:minor>0</rem:minor>
<rem:date>
<rem:year>2018</rem:year>
<rem:month>8</rem:month>
<rem:day>22</rem:day>
</rem:date>
</rem:version>
<rem:authors stakeholders ="STK-0003 STK-0002 STK-0001 STK-0004 "/>
<rem:sources stakeholders ="STK-0002 "/>
<rem:comments>
Ninguno</rem:comments>
<rem:importance value = "IMV-0002"/>
<rem:urgency value = "URV-0002"/>
<rem:status value = "STV-0002"/>
<rem:stability value = "SBV-0004"/>
<rem:description>
tener la capacidad de intercambiar información con otros sistemas y componentes.</rem:description>
</rem:nonFunctionalRequirement>
</rem:section>
<rem:section
 oid = "SEC-0014">
<rem:name>
Fiabilidad</rem:name>
<rem:version>
<rem:major>1</rem:major>
<rem:minor>0</rem:minor>
<rem:date>
<rem:year>2018</rem:year>
<rem:month>8</rem:month>
<rem:day>29</rem:day>
</rem:date>
</rem:version>
<rem:comments>
Ninguno</rem:comments>
<rem:level>3</rem:level>
<rem:number>5.3.2 </rem:number>
<rem:nonFunctionalRequirement
 oid = "NFR-0003">
<rem:name>
Madurez</rem:name>
<rem:version>
<rem:major>1</rem:major>
<rem:minor>0</rem:minor>
<rem:date>
<rem:year>2018</rem:year>
<rem:month>8</rem:month>
<rem:day>29</rem:day>
</rem:date>
</rem:version>
<rem:authors stakeholders ="STK-0003 STK-0002 STK-0001 STK-0004 "/>
<rem:sources stakeholders ="STK-0002 "/>
<rem:comments>
Ninguno</rem:comments>
<rem:importance value = "IMV-0002"/>
<rem:urgency value = "URV-0002"/>
<rem:status value = "STV-0002"/>
<rem:stability value = "SBV-0004"/>
<rem:description>
tener la capacidad de satisfacer las necesidades de fiabilidad en condiciones normales.</rem:description>
</rem:nonFunctionalRequirement>
<rem:nonFunctionalRequirement
 oid = "NFR-0004">
<rem:name>
Disponibilidad</rem:name>
<rem:version>
<rem:major>1</rem:major>
<rem:minor>0</rem:minor>
<rem:date>
<rem:year>2018</rem:year>
<rem:month>8</rem:month>
<rem:day>29</rem:day>
</rem:date>
</rem:version>
<rem:authors stakeholders ="STK-0003 STK-0002 STK-0001 STK-0004 "/>
<rem:sources stakeholders ="STK-0002 "/>
<rem:comments>
Ninguno</rem:comments>
<rem:importance value = "IMV-0002"/>
<rem:urgency value = "URV-0002"/>
<rem:status value = "STV-0002"/>
<rem:stability value = "SBV-0004"/>
<rem:description>
tener la capacidad de estar operativo y accesible para su uso cuando se requiere.</rem:description>
</rem:nonFunctionalRequirement>
<rem:nonFunctionalRequirement
 oid = "NFR-0005">
<rem:name>
Tolerancia a fallos</rem:name>
<rem:version>
<rem:major>1</rem:major>
<rem:minor>0</rem:minor>
<rem:date>
<rem:year>2018</rem:year>
<rem:month>8</rem:month>
<rem:day>29</rem:day>
</rem:date>
</rem:version>
<rem:authors stakeholders ="STK-0003 STK-0002 STK-0001 STK-0004 "/>
<rem:sources stakeholders ="STK-0002 "/>
<rem:comments>
Ninguno</rem:comments>
<rem:importance value = "IMV-0002"/>
<rem:urgency value = "URV-0002"/>
<rem:status value = "STV-0002"/>
<rem:stability value = "SBV-0004"/>
<rem:description>
tener la capacidad para operar según lo previsto en presencia de fallos hardware o software.</rem:description>
</rem:nonFunctionalRequirement>
</rem:section>
<rem:section
 oid = "SEC-0015">
<rem:name>
Seguridad</rem:name>
<rem:version>
<rem:major>1</rem:major>
<rem:minor>0</rem:minor>
<rem:date>
<rem:year>2018</rem:year>
<rem:month>8</rem:month>
<rem:day>29</rem:day>
</rem:date>
</rem:version>
<rem:comments>
Ninguno</rem:comments>
<rem:level>3</rem:level>
<rem:number>5.3.3 </rem:number>
<rem:nonFunctionalRequirement
 oid = "NFR-0006">
<rem:name>
Autenticidad</rem:name>
<rem:version>
<rem:major>1</rem:major>
<rem:minor>0</rem:minor>
<rem:date>
<rem:year>2018</rem:year>
<rem:month>8</rem:month>
<rem:day>29</rem:day>
</rem:date>
</rem:version>
<rem:authors stakeholders ="STK-0003 STK-0002 STK-0001 STK-0004 "/>
<rem:sources stakeholders ="STK-0002 "/>
<rem:comments>
Ninguno</rem:comments>
<rem:importance value = "IMV-0002"/>
<rem:urgency value = "URV-0002"/>
<rem:status value = "STV-0002"/>
<rem:stability value = "SBV-0004"/>
<rem:description>
tener la capacidad  de demostrar la identidad de los usuarios.</rem:description>
</rem:nonFunctionalRequirement>
</rem:section>
<rem:section
 oid = "SEC-0016">
<rem:name>
Mantenibilidad</rem:name>
<rem:version>
<rem:major>1</rem:major>
<rem:minor>0</rem:minor>
<rem:date>
<rem:year>2018</rem:year>
<rem:month>8</rem:month>
<rem:day>29</rem:day>
</rem:date>
</rem:version>
<rem:comments>
Ninguno</rem:comments>
<rem:level>3</rem:level>
<rem:number>5.3.4 </rem:number>
<rem:nonFunctionalRequirement
 oid = "NFR-0008">
<rem:name>
Modularidad</rem:name>
<rem:version>
<rem:major>1</rem:major>
<rem:minor>0</rem:minor>
<rem:date>
<rem:year>2018</rem:year>
<rem:month>8</rem:month>
<rem:day>29</rem:day>
</rem:date>
</rem:version>
<rem:authors stakeholders ="STK-0003 STK-0002 STK-0001 STK-0004 "/>
<rem:sources stakeholders ="STK-0002 "/>
<rem:comments>
Ninguno</rem:comments>
<rem:importance value = "IMV-0002"/>
<rem:urgency value = "URV-0002"/>
<rem:status value = "STV-0002"/>
<rem:stability value = "SBV-0004"/>
<rem:description>
estar compuesto de componentes de tal forma que un cambio en un componente tenga un impacto mínimo en los demás.</rem:description>
</rem:nonFunctionalRequirement>
<rem:nonFunctionalRequirement
 oid = "NFR-0009">
<rem:name>
Reusabilidad</rem:name>
<rem:version>
<rem:major>1</rem:major>
<rem:minor>0</rem:minor>
<rem:date>
<rem:year>2018</rem:year>
<rem:month>8</rem:month>
<rem:day>29</rem:day>
</rem:date>
</rem:version>
<rem:authors stakeholders ="STK-0003 STK-0002 STK-0001 STK-0004 "/>
<rem:sources stakeholders ="STK-0002 "/>
<rem:comments>
Ninguno</rem:comments>
<rem:importance value = "IMV-0002"/>
<rem:urgency value = "URV-0002"/>
<rem:status value = "STV-0002"/>
<rem:stability value = "SBV-0004"/>
<rem:description>
estar compuesto de componentes de tal forma que sea utilizado en más de un sistema software o en la construcción de otros activos.</rem:description>
</rem:nonFunctionalRequirement>
<rem:nonFunctionalRequirement
 oid = "NFR-0010">
<rem:name>
Capacidad para ser modificado</rem:name>
<rem:version>
<rem:major>1</rem:major>
<rem:minor>0</rem:minor>
<rem:date>
<rem:year>2018</rem:year>
<rem:month>8</rem:month>
<rem:day>29</rem:day>
</rem:date>
</rem:version>
<rem:authors stakeholders ="STK-0003 STK-0002 STK-0001 STK-0004 "/>
<rem:sources stakeholders ="STK-0002 "/>
<rem:comments>
Ninguno</rem:comments>
<rem:importance value = "IMV-0002"/>
<rem:urgency value = "URV-0002"/>
<rem:status value = "STV-0002"/>
<rem:stability value = "SBV-0004"/>
<rem:description>
tener la capacidad de ser modificado de forma efectiva y eficiente sin introducir defectos o degradar el desempeño</rem:description>
</rem:nonFunctionalRequirement>
</rem:section>
</rem:section>
<rem:section
 oid = "SEC-0009">
<rem:name>
Requisitos de restricción</rem:name>
<rem:version>
<rem:major>1</rem:major>
<rem:minor>0</rem:minor>
<rem:date>
<rem:year>2018</rem:year>
<rem:month>8</rem:month>
<rem:day>22</rem:day>
</rem:date>
</rem:version>
<rem:comments>
Ninguno</rem:comments>
<rem:level>2</rem:level>
<rem:number>5.4 </rem:number>
<rem:constraintRequirement
 oid = "CRQ-0001">
<rem:name>
Microservicios</rem:name>
<rem:version>
<rem:major>1</rem:major>
<rem:minor>0</rem:minor>
<rem:date>
<rem:year>2018</rem:year>
<rem:month>8</rem:month>
<rem:day>22</rem:day>
</rem:date>
</rem:version>
<rem:authors stakeholders ="STK-0003 STK-0002 STK-0001 STK-0004 "/>
<rem:sources stakeholders ="STK-0002 "/>
<rem:comments>
Ninguno</rem:comments>
<rem:importance value = "IMV-0002"/>
<rem:urgency value = "URV-0002"/>
<rem:status value = "STV-0002"/>
<rem:stability value = "SBV-0004"/>
<rem:description>
usar microservicios.</rem:description>
</rem:constraintRequirement>
<rem:constraintRequirement
 oid = "CRQ-0002">
<rem:name>
<rem:ref oid="GLO-0006">Base</rem:ref> de datos</rem:name>
<rem:version>
<rem:major>1</rem:major>
<rem:minor>0</rem:minor>
<rem:date>
<rem:year>2018</rem:year>
<rem:month>8</rem:month>
<rem:day>22</rem:day>
</rem:date>
</rem:version>
<rem:authors stakeholders ="STK-0003 STK-0002 STK-0001 STK-0004 "/>
<rem:sources stakeholders ="STK-0002 "/>
<rem:comments>
Ninguno</rem:comments>
<rem:importance value = "IMV-0002"/>
<rem:urgency value = "URV-0002"/>
<rem:status value = "STV-0002"/>
<rem:stability value = "SBV-0004"/>
<rem:description>
usar el gestor de <rem:ref oid="GLO-0006">base</rem:ref> de datos MySql.</rem:description>
</rem:constraintRequirement>
<rem:constraintRequirement
 oid = "CRQ-0003">
<rem:name>
Lenguaje de programación</rem:name>
<rem:version>
<rem:major>1</rem:major>
<rem:minor>0</rem:minor>
<rem:date>
<rem:year>2018</rem:year>
<rem:month>8</rem:month>
<rem:day>29</rem:day>
</rem:date>
</rem:version>
<rem:authors stakeholders ="STK-0003 STK-0002 STK-0001 STK-0004 "/>
<rem:sources stakeholders ="STK-0002 "/>
<rem:comments>
Ninguno</rem:comments>
<rem:importance value = "IMV-0002"/>
<rem:urgency value = "URV-0002"/>
<rem:status value = "STV-0002"/>
<rem:stability value = "SBV-0004"/>
<rem:description>
ser desarrollado usando el lenguaje de programación java.</rem:description>
</rem:constraintRequirement>
</rem:section>
</rem:section>
<rem:section
 oid = "SEC-0017">
<rem:name>
Trazabilidad</rem:name>
<rem:version>
<rem:major>1</rem:major>
<rem:minor>0</rem:minor>
<rem:date>
<rem:year>2018</rem:year>
<rem:month>9</rem:month>
<rem:day>4</rem:day>
</rem:date>
</rem:version>
<rem:comments>
Ninguno</rem:comments>
<rem:level>1</rem:level>
<rem:number>6 </rem:number>
<rem:traceabilityMatrix
 oid = "TRM-0001">
<rem:name>
Trazabilidad Requisitos funcionales - Objetivos</rem:name>
<rem:version>
<rem:major>1</rem:major>
<rem:minor>0</rem:minor>
<rem:date>
<rem:year>2018</rem:year>
<rem:month>9</rem:month>
<rem:day>4</rem:day>
</rem:date>
</rem:version>
<rem:comments>
Ninguno</rem:comments>
<rem:tr>
<rem:th/>
<rem:th oid ="OBJ-0001"/>
<rem:th oid ="OBJ-0002"/>
<rem:th oid ="OBJ-0003"/>
<rem:th oid ="OBJ-0004"/>
<rem:th oid ="OBJ-0005"/>
<rem:th oid ="OBJ-0006"/>
</rem:tr>
<rem:tr>
<rem:th oid ="FRQ-0001"/>
<rem:td mark ="no"/>
<rem:td mark ="yes"/>
<rem:td mark ="no"/>
<rem:td mark ="no"/>
<rem:td mark ="no"/>
<rem:td mark ="no"/>
</rem:tr>
<rem:tr>
<rem:th oid ="FRQ-0002"/>
<rem:td mark ="no"/>
<rem:td mark ="no"/>
<rem:td mark ="yes"/>
<rem:td mark ="no"/>
<rem:td mark ="no"/>
<rem:td mark ="no"/>
</rem:tr>
<rem:tr>
<rem:th oid ="FRQ-0003"/>
<rem:td mark ="no"/>
<rem:td mark ="no"/>
<rem:td mark ="no"/>
<rem:td mark ="yes"/>
<rem:td mark ="no"/>
<rem:td mark ="no"/>
</rem:tr>
<rem:tr>
<rem:th oid ="FRQ-0004"/>
<rem:td mark ="no"/>
<rem:td mark ="no"/>
<rem:td mark ="no"/>
<rem:td mark ="no"/>
<rem:td mark ="yes"/>
<rem:td mark ="no"/>
</rem:tr>
<rem:tr>
<rem:th oid ="FRQ-0005"/>
<rem:td mark ="no"/>
<rem:td mark ="no"/>
<rem:td mark ="no"/>
<rem:td mark ="no"/>
<rem:td mark ="no"/>
<rem:td mark ="yes"/>
</rem:tr>
<rem:tr>
<rem:th oid ="FRQ-0007"/>
<rem:td mark ="no"/>
<rem:td mark ="no"/>
<rem:td mark ="yes"/>
<rem:td mark ="no"/>
<rem:td mark ="no"/>
<rem:td mark ="no"/>
</rem:tr>
<rem:tr>
<rem:th oid ="FRQ-0008"/>
<rem:td mark ="no"/>
<rem:td mark ="no"/>
<rem:td mark ="yes"/>
<rem:td mark ="no"/>
<rem:td mark ="no"/>
<rem:td mark ="no"/>
</rem:tr>
<rem:tr>
<rem:th oid ="FRQ-0009"/>
<rem:td mark ="no"/>
<rem:td mark ="no"/>
<rem:td mark ="yes"/>
<rem:td mark ="no"/>
<rem:td mark ="no"/>
<rem:td mark ="no"/>
</rem:tr>
<rem:tr>
<rem:th oid ="FRQ-0010"/>
<rem:td mark ="no"/>
<rem:td mark ="no"/>
<rem:td mark ="no"/>
<rem:td mark ="yes"/>
<rem:td mark ="no"/>
<rem:td mark ="no"/>
</rem:tr>
<rem:tr>
<rem:th oid ="FRQ-0012"/>
<rem:td mark ="no"/>
<rem:td mark ="no"/>
<rem:td mark ="no"/>
<rem:td mark ="yes"/>
<rem:td mark ="no"/>
<rem:td mark ="no"/>
</rem:tr>
<rem:tr>
<rem:th oid ="FRQ-0015"/>
<rem:td mark ="no"/>
<rem:td mark ="no"/>
<rem:td mark ="no"/>
<rem:td mark ="no"/>
<rem:td mark ="yes"/>
<rem:td mark ="no"/>
</rem:tr>
<rem:tr>
<rem:th oid ="FRQ-0016"/>
<rem:td mark ="no"/>
<rem:td mark ="no"/>
<rem:td mark ="no"/>
<rem:td mark ="no"/>
<rem:td mark ="yes"/>
<rem:td mark ="no"/>
</rem:tr>
<rem:tr>
<rem:th oid ="FRQ-0017"/>
<rem:td mark ="no"/>
<rem:td mark ="no"/>
<rem:td mark ="no"/>
<rem:td mark ="no"/>
<rem:td mark ="yes"/>
<rem:td mark ="no"/>
</rem:tr>
<rem:tr>
<rem:th oid ="FRQ-0018"/>
<rem:td mark ="no"/>
<rem:td mark ="no"/>
<rem:td mark ="no"/>
<rem:td mark ="no"/>
<rem:td mark ="no"/>
<rem:td mark ="yes"/>
</rem:tr>
<rem:tr>
<rem:th oid ="FRQ-0019"/>
<rem:td mark ="no"/>
<rem:td mark ="no"/>
<rem:td mark ="no"/>
<rem:td mark ="no"/>
<rem:td mark ="no"/>
<rem:td mark ="yes"/>
</rem:tr>
<rem:tr>
<rem:th oid ="FRQ-0020"/>
<rem:td mark ="no"/>
<rem:td mark ="yes"/>
<rem:td mark ="no"/>
<rem:td mark ="no"/>
<rem:td mark ="no"/>
<rem:td mark ="no"/>
</rem:tr>
<rem:tr>
<rem:th oid ="FRQ-0021"/>
<rem:td mark ="no"/>
<rem:td mark ="yes"/>
<rem:td mark ="no"/>
<rem:td mark ="no"/>
<rem:td mark ="no"/>
<rem:td mark ="no"/>
</rem:tr>
<rem:tr>
<rem:th oid ="FRQ-0022"/>
<rem:td mark ="no"/>
<rem:td mark ="no"/>
<rem:td mark ="no"/>
<rem:td mark ="yes"/>
<rem:td mark ="no"/>
<rem:td mark ="no"/>
</rem:tr>
<rem:tr>
<rem:th oid ="FRQ-0023"/>
<rem:td mark ="no"/>
<rem:td mark ="no"/>
<rem:td mark ="no"/>
<rem:td mark ="yes"/>
<rem:td mark ="no"/>
<rem:td mark ="no"/>
</rem:tr>
<rem:tr>
<rem:th oid ="FRQ-0024"/>
<rem:td mark ="no"/>
<rem:td mark ="no"/>
<rem:td mark ="no"/>
<rem:td mark ="no"/>
<rem:td mark ="yes"/>
<rem:td mark ="no"/>
</rem:tr>
</rem:traceabilityMatrix>
</rem:section>
<rem:section
 oid = "SEC-0010">
<rem:name>
Glosario</rem:name>
<rem:version>
<rem:major>1</rem:major>
<rem:minor>0</rem:minor>
<rem:date>
<rem:year>2018</rem:year>
<rem:month>8</rem:month>
<rem:day>22</rem:day>
</rem:date>
</rem:version>
<rem:comments>
Ninguno</rem:comments>
<rem:level>1</rem:level>
<rem:number>7 </rem:number>
<rem:glossaryItem
 oid = "GLO-0001">
<rem:name>
<rem:ref oid="GLO-0001">Mercancía</rem:ref></rem:name>
<rem:version>
<rem:major>1</rem:major>
<rem:minor>0</rem:minor>
<rem:date>
<rem:year>2018</rem:year>
<rem:month>8</rem:month>
<rem:day>22</rem:day>
</rem:date>
</rem:version>
<rem:comments>
Ninguno</rem:comments>
<rem:text>Productos o materias primas, objetos, etc.</rem:text>
</rem:glossaryItem>
<rem:glossaryItem
 oid = "GLO-0002">
<rem:name>
<rem:ref oid="GLO-0002">Remitente</rem:ref></rem:name>
<rem:version>
<rem:major>1</rem:major>
<rem:minor>0</rem:minor>
<rem:date>
<rem:year>2018</rem:year>
<rem:month>8</rem:month>
<rem:day>22</rem:day>
</rem:date>
</rem:version>
<rem:comments>
Ninguno</rem:comments>
<rem:text>Persona que envía la <rem:ref oid="GLO-0001">mercancía</rem:ref>.</rem:text>
</rem:glossaryItem>
<rem:glossaryItem
 oid = "GLO-0003">
<rem:name>
<rem:ref oid="GLO-0003">Destinatario</rem:ref></rem:name>
<rem:version>
<rem:major>1</rem:major>
<rem:minor>0</rem:minor>
<rem:date>
<rem:year>2018</rem:year>
<rem:month>8</rem:month>
<rem:day>22</rem:day>
</rem:date>
</rem:version>
<rem:comments>
Ninguno</rem:comments>
<rem:text>Persona que recibe la <rem:ref oid="GLO-0001">mercancía</rem:ref>.</rem:text>
</rem:glossaryItem>
<rem:glossaryItem
 oid = "GLO-0004">
<rem:name>
<rem:ref oid="GLO-0004">Ventanilla</rem:ref></rem:name>
<rem:version>
<rem:major>1</rem:major>
<rem:minor>0</rem:minor>
<rem:date>
<rem:year>2018</rem:year>
<rem:month>8</rem:month>
<rem:day>27</rem:day>
</rem:date>
</rem:version>
<rem:comments>
Ninguno</rem:comments>
<rem:text>Lugar de atención al cliente en una terminal del operador logístico.</rem:text>
</rem:glossaryItem>
<rem:glossaryItem
 oid = "GLO-0005">
<rem:name>
<rem:ref oid="GLO-0005">Dirección de origen</rem:ref></rem:name>
<rem:version>
<rem:major>1</rem:major>
<rem:minor>0</rem:minor>
<rem:date>
<rem:year>2018</rem:year>
<rem:month>8</rem:month>
<rem:day>27</rem:day>
</rem:date>
</rem:version>
<rem:comments>
Ninguno</rem:comments>
<rem:text>Dirección de recogida de <rem:ref oid="GLO-0001">mercancía</rem:ref> en el lugar de origen.</rem:text>
</rem:glossaryItem>
<rem:glossaryItem
 oid = "GLO-0006">
<rem:name>
<rem:ref oid="GLO-0006">Base</rem:ref></rem:name>
<rem:version>
<rem:major>1</rem:major>
<rem:minor>0</rem:minor>
<rem:date>
<rem:year>2018</rem:year>
<rem:month>8</rem:month>
<rem:day>27</rem:day>
</rem:date>
</rem:version>
<rem:comments>
Ninguno</rem:comments>
<rem:text>Sucursal del operador logístico dentro de otra empresa.</rem:text>
</rem:glossaryItem>
<rem:glossaryItem
 oid = "GLO-0007">
<rem:name>
<rem:ref oid="GLO-0007">Tripulación</rem:ref></rem:name>
<rem:version>
<rem:major>1</rem:major>
<rem:minor>0</rem:minor>
<rem:date>
<rem:year>2018</rem:year>
<rem:month>9</rem:month>
<rem:day>23</rem:day>
</rem:date>
</rem:version>
<rem:comments>
Ninguno</rem:comments>
<rem:text>Personal del operador encargado de realizar un proceso en todo el trámite del transporte de <rem:ref oid="GLO-0001">mercancía</rem:ref>.</rem:text>
</rem:glossaryItem>
</rem:section>
</rem:c_requirementsSpecification>
<rem:d_requirementsSpecification oid = "DRS-0002">
<rem:name>Documento de Análisis del Sistema</rem:name>
<rem:version>
<rem:major>1</rem:major>
<rem:minor>0</rem:minor>
<rem:date>
<rem:year>2018</rem:year>
<rem:month>8</rem:month>
<rem:day>21</rem:day>
</rem:date>
</rem:version>
<rem:comments>
Ninguno
</rem:comments>
</rem:d_requirementsSpecification>
<rem:defectsSpecification oid = "DFS-0003">
<rem:name>Registro de Conflictos y Defectos</rem:name>
<rem:version>
<rem:major>1</rem:major>
<rem:minor>0</rem:minor>
<rem:date>
<rem:year>2018</rem:year>
<rem:month>8</rem:month>
<rem:day>21</rem:day>
</rem:date>
</rem:version>
<rem:comments>
Ninguno
</rem:comments>
</rem:defectsSpecification>
<rem:changeRequestsSpecification oid = "CHS-0004">
<rem:name>Registro de Peticiones de Cambio</rem:name>
<rem:version>
<rem:major>1</rem:major>
<rem:minor>0</rem:minor>
<rem:date>
<rem:year>2018</rem:year>
<rem:month>8</rem:month>
<rem:day>21</rem:day>
</rem:date>
</rem:version>
<rem:comments>
Ninguno
</rem:comments>
</rem:changeRequestsSpecification>
<rem:trace source = "FRQ-0023"  target = "OBJ-0004" >
<rem:isChecked/>
</rem:trace>
<rem:trace source = "FRQ-0024"  target = "OBJ-0005" >
<rem:isChecked/>
</rem:trace>
<rem:trace source = "FRQ-0010"  target = "OBJ-0004" >
<rem:isChecked/>
</rem:trace>
<rem:trace source = "OBJ-0006"  target = "OBJ-0001" >
<rem:isChecked/>
</rem:trace>
<rem:trace source = "FRQ-0008"  target = "OBJ-0003" >
<rem:isChecked/>
</rem:trace>
<rem:trace source = "OBJ-0005"  target = "OBJ-0001" >
<rem:isChecked/>
</rem:trace>
<rem:trace source = "FRQ-0012"  target = "OBJ-0004" >
<rem:isChecked/>
</rem:trace>
<rem:trace source = "FRQ-0004"  target = "OBJ-0005" >
<rem:isChecked/>
</rem:trace>
<rem:trace source = "OBJ-0002"  target = "OBJ-0001" >
<rem:isChecked/>
</rem:trace>
<rem:trace source = "FRQ-0007"  target = "OBJ-0003" >
<rem:isChecked/>
</rem:trace>
<rem:trace source = "FRQ-0003"  target = "OBJ-0004" >
<rem:isChecked/>
</rem:trace>
<rem:trace source = "OBJ-0004"  target = "OBJ-0001" >
<rem:isChecked/>
</rem:trace>
<rem:trace source = "FRQ-0001"  target = "OBJ-0002" >
<rem:isChecked/>
</rem:trace>
<rem:trace source = "FRQ-0002"  target = "OBJ-0003" >
<rem:isChecked/>
</rem:trace>
<rem:trace source = "OBJ-0003"  target = "OBJ-0001" >
<rem:isChecked/>
</rem:trace>
<rem:trace source = "FRQ-0009"  target = "OBJ-0003" >
<rem:isChecked/>
</rem:trace>
<rem:trace source = "FRQ-0020"  target = "OBJ-0002" >
<rem:isChecked/>
</rem:trace>
<rem:trace source = "FRQ-0016"  target = "OBJ-0005" >
<rem:isChecked/>
</rem:trace>
<rem:trace source = "FRQ-0022"  target = "OBJ-0004" >
<rem:isChecked/>
</rem:trace>
<rem:trace source = "FRQ-0015"  target = "OBJ-0005" >
<rem:isChecked/>
</rem:trace>
<rem:trace source = "FRQ-0021"  target = "OBJ-0002" >
<rem:isChecked/>
</rem:trace>
<rem:trace source = "FRQ-0017"  target = "OBJ-0005" >
<rem:isChecked/>
</rem:trace>
<rem:trace source = "FRQ-0018"  target = "OBJ-0006" >
<rem:isChecked/>
</rem:trace>
<rem:trace source = "FRQ-0005"  target = "OBJ-0006" >
<rem:isChecked/>
</rem:trace>
<rem:trace source = "FRQ-0019"  target = "OBJ-0006" >
<rem:isChecked/>
</rem:trace>
<rem:predefinedValueTypes>
<rem:predefinedValueType
 oid = "PVT-0004">
<rem:name>
String</rem:name>
<rem:version>
<rem:major>1</rem:major>
<rem:minor>0</rem:minor>
<rem:date>
<rem:year>2000</rem:year>
<rem:month>10</rem:month>
<rem:day>30</rem:day>
</rem:date>
</rem:version>
<rem:comments>
Predefined OCL type</rem:comments>
<rem:description>
Alphanumeric strings</rem:description>
<rem:definition>
(null)
</rem:definition>
</rem:predefinedValueType>
<rem:predefinedValueType
 oid = "PVT-0003">
<rem:name>
Natural</rem:name>
<rem:version>
<rem:major>1</rem:major>
<rem:minor>0</rem:minor>
<rem:date>
<rem:year>2000</rem:year>
<rem:month>10</rem:month>
<rem:day>30</rem:day>
</rem:date>
</rem:version>
<rem:comments>
Predefined OCL type</rem:comments>
<rem:description>
Natural numbers</rem:description>
<rem:definition>
(null)
</rem:definition>
</rem:predefinedValueType>
<rem:predefinedValueType
 oid = "PVT-0005">
<rem:name>
Date</rem:name>
<rem:version>
<rem:major>1</rem:major>
<rem:minor>0</rem:minor>
<rem:date>
<rem:year>2000</rem:year>
<rem:month>10</rem:month>
<rem:day>30</rem:day>
</rem:date>
</rem:version>
<rem:comments>
Predefined OCL type (non-standard)</rem:comments>
<rem:description>
Dates</rem:description>
<rem:definition>
(null)
</rem:definition>
</rem:predefinedValueType>
<rem:predefinedValueType
 oid = "PVT-0006">
<rem:name>
Time</rem:name>
<rem:version>
<rem:major>1</rem:major>
<rem:minor>0</rem:minor>
<rem:date>
<rem:year>2000</rem:year>
<rem:month>10</rem:month>
<rem:day>30</rem:day>
</rem:date>
</rem:version>
<rem:comments>
Predefined OCL type (non-standard)</rem:comments>
<rem:description>
Hour:minutes:seconds</rem:description>
<rem:definition>
(null)
</rem:definition>
</rem:predefinedValueType>
<rem:predefinedValueType
 oid = "PVT-0001">
<rem:name>
Real</rem:name>
<rem:version>
<rem:major>1</rem:major>
<rem:minor>0</rem:minor>
<rem:date>
<rem:year>2000</rem:year>
<rem:month>10</rem:month>
<rem:day>30</rem:day>
</rem:date>
</rem:version>
<rem:comments>
Predefined OCL type</rem:comments>
<rem:description>
Real numbers</rem:description>
<rem:definition>
(null)
</rem:definition>
</rem:predefinedValueType>
<rem:predefinedValueType
 oid = "PVT-0002">
<rem:name>
Integer</rem:name>
<rem:version>
<rem:major>1</rem:major>
<rem:minor>0</rem:minor>
<rem:date>
<rem:year>2000</rem:year>
<rem:month>10</rem:month>
<rem:day>30</rem:day>
</rem:date>
</rem:version>
<rem:comments>
Predefined OCL type</rem:comments>
<rem:description>
Integer numbers</rem:description>
<rem:definition>
(null)
</rem:definition>
</rem:predefinedValueType>
</rem:predefinedValueTypes>
<rem:predefinedValues>
<rem:changeRequestStatusValue oid = "CRV-0001">
<rem:name>PD</rem:name>
</rem:changeRequestStatusValue>
<rem:changeRequestStatusValue oid = "CRV-0004">
<rem:name>pendiente de realización</rem:name>
</rem:changeRequestStatusValue>
<rem:changeRequestStatusValue oid = "CRV-0006">
<rem:name>rechazado</rem:name>
</rem:changeRequestStatusValue>
<rem:changeRequestStatusValue oid = "CRV-0003">
<rem:name>pendiente de aprobar/rechazar</rem:name>
</rem:changeRequestStatusValue>
<rem:changeRequestStatusValue oid = "CRV-0002">
<rem:name>pendiente de análisis</rem:name>
</rem:changeRequestStatusValue>
<rem:changeRequestStatusValue oid = "CRV-0005">
<rem:name>verificado</rem:name>
</rem:changeRequestStatusValue>
<rem:conflictStatusValue oid = "CSV-0002">
<rem:name>no resuelto</rem:name>
</rem:conflictStatusValue>
<rem:conflictStatusValue oid = "CSV-0004">
<rem:name>resuelto</rem:name>
</rem:conflictStatusValue>
<rem:conflictStatusValue oid = "CSV-0003">
<rem:name>en proceso de negociación</rem:name>
</rem:conflictStatusValue>
<rem:conflictStatusValue oid = "CSV-0001">
<rem:name>PD</rem:name>
</rem:conflictStatusValue>
<rem:defectStatusValue oid = "DSV-0004">
<rem:name>eliminado</rem:name>
</rem:defectStatusValue>
<rem:defectStatusValue oid = "DSV-0002">
<rem:name>no eliminado</rem:name>
</rem:defectStatusValue>
<rem:defectStatusValue oid = "DSV-0003">
<rem:name>en proceso de negociación</rem:name>
</rem:defectStatusValue>
<rem:defectStatusValue oid = "DSV-0001">
<rem:name>PD</rem:name>
</rem:defectStatusValue>
<rem:defectTypeValue oid = "DTV-0016">
<rem:name>No rastreabilidad</rem:name>
<rem:description>
<![CDATA[El requisito o requisitos no están trazados hacia sus orígenes, bien requisitos de nivel superior (objetivos), bien clientes y usuarios]]>
</rem:description>
</rem:defectTypeValue>
<rem:defectTypeValue oid = "DTV-0023">
<rem:name>Otro</rem:name>
<rem:description>
<![CDATA[El requisito o requisitos presentan otro tipo de defecto]]>
</rem:description>
</rem:defectTypeValue>
<rem:defectTypeValue oid = "DTV-0017">
<rem:name>Organización incorrecta</rem:name>
<rem:description>
<![CDATA[El requisito o requisitos no están organizados correctamente según la normativa aplicada o el documento no contiene las secciones obligatorias]]>
</rem:description>
</rem:defectTypeValue>
<rem:defectTypeValue oid = "DTV-0008">
<rem:name>Verbosidad excesiva</rem:name>
<rem:description>
<![CDATA[El requisito o requisitos pueden expresarse de forma más concisa sin alterar su significado]]>
</rem:description>
</rem:defectTypeValue>
<rem:defectTypeValue oid = "DTV-0006">
<rem:name>Inconsistencia</rem:name>
<rem:description>
<![CDATA[El requisito o requisitos no son consistentes, es decir, presentan contradicciones internas o entre varios]]>
</rem:description>
</rem:defectTypeValue>
<rem:defectTypeValue oid = "DTV-0009">
<rem:name>Dependiente del diseño</rem:name>
<rem:description>
<![CDATA[El requisito o requisitos incluyen elementos dependientes del diseño del sistema]]>
</rem:description>
</rem:defectTypeValue>
<rem:defectTypeValue oid = "DTV-0005">
<rem:name>No verificabilidad</rem:name>
<rem:description>
<![CDATA[No se puede comprobar que el sistema satisface el requisito o requisitos]]>
</rem:description>
</rem:defectTypeValue>
<rem:defectTypeValue oid = "DTV-0007">
<rem:name>No implementabilidad</rem:name>
<rem:description>
<![CDATA[El requisito o requisitos no pueden ser implementados con la tecnología actual o dentro de un coste razonable]]>
</rem:description>
</rem:defectTypeValue>
<rem:defectTypeValue oid = "DTV-0004">
<rem:name>Incomprensibilidad</rem:name>
<rem:description>
<![CDATA[El requisito o requisitos no pueden ser entendidos por algún lector]]>
</rem:description>
</rem:defectTypeValue>
<rem:defectTypeValue oid = "DTV-0013">
<rem:name>Prioridad no establecida</rem:name>
<rem:description>
<![CDATA[El requisito o requisitos no tienen establecida su prioridad, es decir, su importancia y su urgencia]]>
</rem:description>
</rem:defectTypeValue>
<rem:defectTypeValue oid = "DTV-0011">
<rem:name>Imprecisión</rem:name>
<rem:description>
<![CDATA[El requisito o requisitos no se expresan de forma precisa, es decir, usando cantidades numéricas siempre que sea posible con el nivel adecuado de precisión]]>
</rem:description>
</rem:defectTypeValue>
<rem:defectTypeValue oid = "DTV-0015">
<rem:name>Nivel incorrecto de detalle</rem:name>
<rem:description>
<![CDATA[El requisito o requisitos no están expresados con el nivel adecuado de detalle, es decir, son demasiado abstractos o demasiado detallados]]>
</rem:description>
</rem:defectTypeValue>
<rem:defectTypeValue oid = "DTV-0012">
<rem:name>Incompleción</rem:name>
<rem:description>
<![CDATA[El requisito o requisitos no describen todo lo que el sistema se supone que deberá hacer, no describen las respuestas del sistema a todas las posibles situaciones o incluyen elementos por determinar (PD)]]>
</rem:description>
</rem:defectTypeValue>
<rem:defectTypeValue oid = "DTV-0010">
<rem:name>Redundancia</rem:name>
<rem:description>
<![CDATA[El requisito o requisitos son redundantes o contienen elementos redundantes]]>
</rem:description>
</rem:defectTypeValue>
<rem:defectTypeValue oid = "DTV-0014">
<rem:name>Estabilidad no establecida</rem:name>
<rem:description>
<![CDATA[El requisito o requisitos no tienen estimada su estabilidad]]>
</rem:description>
</rem:defectTypeValue>
<rem:defectTypeValue oid = "DTV-0003">
<rem:name>No necesidad</rem:name>
<rem:description>
<![CDATA[El requisito o requisitos no son necesarios porque no contribuyen a satisfacer ninguna necesidad de clientes o usuarios]]>
</rem:description>
</rem:defectTypeValue>
<rem:defectTypeValue oid = "DTV-0002">
<rem:name>Ambigüedad</rem:name>
<rem:description>
<![CDATA[El requisito o requisitos, aunque comprensibles, tienen más de una interpretación posible]]>
</rem:description>
</rem:defectTypeValue>
<rem:defectTypeValue oid = "DTV-0001">
<rem:name>PD</rem:name>
<rem:description>
<![CDATA[Por Determinar]]>
</rem:description>
</rem:defectTypeValue>
<rem:importanceValue oid = "IMV-0002">
<rem:name>vital</rem:name>
</rem:importanceValue>
<rem:importanceValue oid = "IMV-0001">
<rem:name>PD</rem:name>
</rem:importanceValue>
<rem:importanceValue oid = "IMV-0003">
<rem:name>importante</rem:name>
</rem:importanceValue>
<rem:importanceValue oid = "IMV-0004">
<rem:name>quedaría bien</rem:name>
</rem:importanceValue>
<rem:stabilityValue oid = "SBV-0002">
<rem:name>baja</rem:name>
</rem:stabilityValue>
<rem:stabilityValue oid = "SBV-0004">
<rem:name>alta</rem:name>
</rem:stabilityValue>
<rem:stabilityValue oid = "SBV-0001">
<rem:name>PD</rem:name>
</rem:stabilityValue>
<rem:stabilityValue oid = "SBV-0003">
<rem:name>media</rem:name>
</rem:stabilityValue>
<rem:statusValue oid = "STV-0001">
<rem:name>PD</rem:name>
</rem:statusValue>
<rem:statusValue oid = "STV-0002">
<rem:name>en construcción</rem:name>
</rem:statusValue>
<rem:statusValue oid = "STV-0004">
<rem:name>pendiente de validación</rem:name>
</rem:statusValue>
<rem:statusValue oid = "STV-0003">
<rem:name>pendiente de verificación</rem:name>
</rem:statusValue>
<rem:statusValue oid = "STV-0005">
<rem:name>validado</rem:name>
</rem:statusValue>
<rem:terminationValue oid = "TEV-0001">
<rem:name>PD</rem:name>
</rem:terminationValue>
<rem:terminationValue oid = "TEV-0002">
<rem:name>continúa</rem:name>
</rem:terminationValue>
<rem:terminationValue oid = "TEV-0003">
<rem:name>queda sin efecto</rem:name>
</rem:terminationValue>
<rem:timeUnitValue oid = "TUV-0007">
<rem:name>semana(s)</rem:name>
</rem:timeUnitValue>
<rem:timeUnitValue oid = "TUV-0001">
<rem:name>PD</rem:name>
</rem:timeUnitValue>
<rem:timeUnitValue oid = "TUV-0002">
<rem:name>año(s)</rem:name>
</rem:timeUnitValue>
<rem:timeUnitValue oid = "TUV-0008">
<rem:name>día(s)</rem:name>
</rem:timeUnitValue>
<rem:timeUnitValue oid = "TUV-0005">
<rem:name>mes(es)</rem:name>
</rem:timeUnitValue>
<rem:timeUnitValue oid = "TUV-0013">
<rem:name>centésima(s) de segundo</rem:name>
</rem:timeUnitValue>
<rem:timeUnitValue oid = "TUV-0012">
<rem:name>décima(s) de segundo</rem:name>
</rem:timeUnitValue>
<rem:timeUnitValue oid = "TUV-0011">
<rem:name>segundo(s)</rem:name>
</rem:timeUnitValue>
<rem:timeUnitValue oid = "TUV-0014">
<rem:name>milisegundo(s)</rem:name>
</rem:timeUnitValue>
<rem:timeUnitValue oid = "TUV-0009">
<rem:name>hora(s)</rem:name>
</rem:timeUnitValue>
<rem:timeUnitValue oid = "TUV-0010">
<rem:name>minuto(s)</rem:name>
</rem:timeUnitValue>
<rem:urgencyValue oid = "URV-0001">
<rem:name>PD</rem:name>
</rem:urgencyValue>
<rem:urgencyValue oid = "URV-0002">
<rem:name>inmediatamente</rem:name>
</rem:urgencyValue>
<rem:urgencyValue oid = "URV-0003">
<rem:name>hay presión</rem:name>
</rem:urgencyValue>
<rem:urgencyValue oid = "URV-0004">
<rem:name>puede esperar</rem:name>
</rem:urgencyValue>
</rem:predefinedValues>
</rem:requirementsProject>
